{
  "data": {
    "article": {},
    "attachments": {
      "media_keys": [
        "3_2072313320632401920"
      ],
      "media_source_tweet_id": [
        "2072313422524637523"
      ]
    },
    "author_id": "1280001743162609664",
    "conversation_id": "2072580063279931598",
    "created_at": "2026-07-02T07:16:08.000Z",
    "edit_controls": {
      "editable_until": "2026-07-02T08:16:08.000Z",
      "edits_remaining": 5,
      "is_edit_eligible": false
    },
    "edit_history_tweet_ids": [
      "2072580063279931598"
    ],
    "entities": {
      "mentions": [
        {
          "end": 12,
          "id": "1893946859057721344",
          "start": 3,
          "username": "arc_8bit"
        },
        {
          "end": 34,
          "id": "1637140231869857793",
          "start": 23,
          "username": "xilige0629"
        }
      ],
      "urls": [
        {
          "display_url": "pic.x.com/n8wUPGl6vX",
          "end": 58,
          "expanded_url": "https://x.com/arc_8bit/status/2072313422524637523/photo/1",
          "media_key": "3_2072313320632401920",
          "start": 35,
          "url": "https://t.co/n8wUPGl6vX"
        }
      ]
    },
    "geo": {},
    "id": "2072580063279931598",
    "lang": "zh",
    "note_tweet": {
      "entities": {}
    },
    "possibly_sensitive": false,
    "public_metrics": {
      "bookmark_count": 0,
      "impression_count": 0,
      "like_count": 0,
      "quote_count": 0,
      "reply_count": 0,
      "retweet_count": 12
    },
    "referenced_tweets": [
      {
        "id": "2072313422524637523",
        "type": "retweeted"
      }
    ],
    "reply_settings": "everyone",
    "text": "RT @arc_8bit: 好不好嘛~\n\n📷：@xilige0629 https://t.co/n8wUPGl6vX"
  },
  "includes": {
    "media": [
      {
        "height": 4096,
        "media_key": "3_2072313320632401920",
        "public_metrics": {},
        "type": "photo",
        "url": "https://pbs.twimg.com/media/HMJV_EuawAADg3y.jpg",
        "width": 3072
      }
    ],
    "tweets": [
      {
        "article": {},
        "attachments": {
          "media_keys": [
            "3_2072313320632401920"
          ],
          "media_source_tweet_id": [
            "2072313422524637523"
          ]
        },
        "author_id": "1280001743162609664",
        "conversation_id": "2072580063279931598",
        "created_at": "2026-07-02T07:16:08.000Z",
        "edit_controls": {
          "editable_until": "2026-07-02T08:16:08.000Z",
          "edits_remaining": 5,
          "is_edit_eligible": false
        },
        "edit_history_tweet_ids": [
          "2072580063279931598"
        ],
        "entities": {
          "mentions": [
            {
              "end": 12,
              "id": "1893946859057721344",
              "start": 3,
              "username": "arc_8bit"
            },
            {
              "end": 34,
              "id": "1637140231869857793",
              "start": 23,
              "username": "xilige0629"
            }
          ],
          "urls": [
            {
              "display_url": "pic.x.com/n8wUPGl6vX",
              "end": 58,
              "expanded_url": "https://x.com/arc_8bit/status/2072313422524637523/photo/1",
              "media_key": "3_2072313320632401920",
              "start": 35,
              "url": "https://t.co/n8wUPGl6vX"
            }
          ]
        },
        "geo": {},
        "id": "2072580063279931598",
        "lang": "zh",
        "note_tweet": {
          "entities": {}
        },
        "possibly_sensitive": false,
        "public_metrics": {
          "bookmark_count": 0,
          "impression_count": 0,
          "like_count": 0,
          "quote_count": 0,
          "reply_count": 0,
          "retweet_count": 12
        },
        "referenced_tweets": [
          {
            "id": "2072313422524637523",
            "type": "retweeted"
          }
        ],
        "reply_settings": "everyone",
        "text": "RT @arc_8bit: 好不好嘛~\n\n📷：@xilige0629 https://t.co/n8wUPGl6vX"
      },
      {
        "article": {},
        "attachments": {
          "media_keys": [
            "3_2072313320632401920"
          ]
        },
        "author_id": "1893946859057721344",
        "conversation_id": "2072313422524637523",
        "created_at": "2026-07-01T13:36:36.000Z",
        "edit_controls": {
          "editable_until": "2026-07-01T14:36:36.000Z",
          "edits_remaining": 5,
          "is_edit_eligible": true
        },
        "edit_history_tweet_ids": [
          "2072313422524637523"
        ],
        "entities": {
          "mentions": [
            {
              "end": 20,
              "id": "1637140231869857793",
              "start": 9,
              "username": "xilige0629"
            }
          ],
          "urls": [
            {
              "display_url": "pic.x.com/n8wUPGl6vX",
              "end": 44,
              "expanded_url": "https://x.com/arc_8bit/status/2072313422524637523/photo/1",
              "media_key": "3_2072313320632401920",
              "start": 21,
              "url": "https://t.co/n8wUPGl6vX"
            }
          ]
        },
        "geo": {},
        "id": "2072313422524637523",
        "lang": "zh",
        "note_tweet": {
          "entities": {}
        },
        "possibly_sensitive": false,
        "public_metrics": {
          "bookmark_count": 23,
          "impression_count": 2034,
          "like_count": 212,
          "quote_count": 0,
          "reply_count": 5,
          "retweet_count": 12
        },
        "reply_settings": "everyone",
        "text": "好不好嘛~\n\n📷：@xilige0629 https://t.co/n8wUPGl6vX"
      }
    ],
    "users": [
      {
        "created_at": "2020-07-06T04:53:06.000Z",
        "derived": {
          "locations": [
            {
              "country_code": "CN",
              "full_name": "Xinpu, Jiangsu Sheng, China",
              "geo": {
                "coordinates": [
                  119.15944,
                  34.59972
                ],
                "type": "Point"
              },
              "locality": "Xinpu",
              "region": "Jiangsu Sheng"
            }
          ]
        },
        "description": "英文名叫Poca\nCN早露泡泡兔\nkiger角色：凑阿库娅，早露\n可爱对象YOYO：@vu_yoyo\n娃图专用号：@Poca5150\n欢迎大家互关贴贴",
        "entities": {
          "description": {
            "mentions": [
              {
                "end": 50,
                "start": 42,
                "username": "vu_yoyo"
              },
              {
                "end": 66,
                "start": 57,
                "username": "Poca5150"
              }
            ]
          }
        },
        "id": "1280001743162609664",
        "location": "香港",
        "name": "是早露泡泡兔呀",
        "pinned_tweet_id": "1563474617657749504",
        "profile_image_url": "https://pbs.twimg.com/profile_images/2051672456298205184/OiCCKyub_normal.jpg",
        "protected": false,
        "public_metrics": {
          "followers_count": 22439,
          "following_count": 9757,
          "like_count": 152847,
          "listed_count": 52,
          "media_count": 5186,
          "tweet_count": 52881
        },
        "url": "",
        "username": "Poca2381",
        "verified": true
      },
      {
        "created_at": "2025-02-24T08:51:43.000Z",
        "description": "kigurumi | 可公开存档点 | 填充物の摄像机 |",
        "entities": {
          "url": {
            "urls": [
              {
                "display_url": "t.me/bit_io_register",
                "end": 23,
                "expanded_url": "https://t.me/bit_io_register",
                "start": 0,
                "url": "https://t.co/uZZpd1Noni"
              }
            ]
          }
        },
        "id": "1893946859057721344",
        "location": "百京",
        "name": "8bit",
        "pinned_tweet_id": "1988065115372237293",
        "profile_image_url": "https://pbs.twimg.com/profile_images/1893947456632561665/w9PL2_Qk_normal.jpg",
        "protected": false,
        "public_metrics": {
          "followers_count": 4091,
          "following_count": 757,
          "like_count": 4714,
          "listed_count": 19,
          "media_count": 120,
          "tweet_count": 471
        },
        "url": "https://t.co/uZZpd1Noni",
        "username": "arc_8bit",
        "verified": false
      },
      {
        "created_at": "2023-03-18T17:14:05.000Z",
        "description": "目前生活在帝都の碳基生物（有几率全球闪现）目前不常用X\n\nWT/WOWS/GTA/WMMT/IDAC都不会打  \n目前在给塑料大头肉色紧身衣变态们当后勤\n\n什么时候变？soon（",
        "id": "1637140231869857793",
        "location": "夏莱",
        "name": "奶油小生",
        "profile_image_url": "https://pbs.twimg.com/profile_images/1864992075487547394/K3UV6yqx_normal.jpg",
        "protected": false,
        "public_metrics": {
          "followers_count": 478,
          "following_count": 340,
          "like_count": 2916,
          "listed_count": 1,
          "media_count": 19,
          "tweet_count": 197
        },
        "url": "",
        "username": "xilige0629",
        "verified": false
      }
    ]
  }
}