{
  "data": {
    "article": {},
    "attachments": {
      "media_keys": [
        "3_2073288166795288577"
      ],
      "media_source_tweet_id": [
        "2073288177650110769"
      ]
    },
    "author_id": "1280001743162609664",
    "conversation_id": "2073775424665165931",
    "created_at": "2026-07-05T14:26:04.000Z",
    "edit_controls": {
      "editable_until": "2026-07-05T15:26:04.000Z",
      "edits_remaining": 5,
      "is_edit_eligible": false
    },
    "edit_history_tweet_ids": [
      "2073775424665165931"
    ],
    "entities": {
      "hashtags": [
        {
          "end": 56,
          "start": 47,
          "tag": "kigurumi"
        },
        {
          "end": 62,
          "start": 57,
          "tag": "着ぐるみ"
        },
        {
          "end": 69,
          "start": 63,
          "tag": "latex"
        }
      ],
      "mentions": [
        {
          "end": 18,
          "id": "821582303235166208",
          "start": 3,
          "username": "GoldSara_Lotus"
        },
        {
          "end": 45,
          "id": "1709241925520531456",
          "start": 35,
          "username": "Blank_qwq"
        }
      ],
      "urls": [
        {
          "display_url": "pic.x.com/e8tDq6GfrG",
          "end": 93,
          "expanded_url": "https://x.com/GoldSara_Lotus/status/2073288177650110769/photo/1",
          "media_key": "3_2073288166795288577",
          "start": 70,
          "url": "https://t.co/e8tDq6GfrG"
        }
      ]
    },
    "geo": {},
    "id": "2073775424665165931",
    "lang": "ja",
    "note_tweet": {
      "entities": {}
    },
    "possibly_sensitive": false,
    "public_metrics": {
      "bookmark_count": 0,
      "impression_count": 0,
      "like_count": 0,
      "quote_count": 0,
      "reply_count": 0,
      "retweet_count": 18
    },
    "referenced_tweets": [
      {
        "id": "2073288177650110769",
        "type": "retweeted"
      }
    ],
    "reply_settings": "everyone",
    "text": "RT @GoldSara_Lotus: 远眺雅拉和雅姆雪山🏔️\n\n📸：@Blank_qwq \n#kigurumi #着ぐるみ #latex https://t.co/e8tDq6GfrG"
  },
  "includes": {
    "media": [
      {
        "height": 1366,
        "media_key": "3_2073288166795288577",
        "public_metrics": {},
        "type": "photo",
        "url": "https://pbs.twimg.com/media/HMXMmlraoAEqebX.jpg",
        "width": 2048
      }
    ],
    "tweets": [
      {
        "article": {},
        "attachments": {
          "media_keys": [
            "3_2073288166795288577"
          ],
          "media_source_tweet_id": [
            "2073288177650110769"
          ]
        },
        "author_id": "1280001743162609664",
        "conversation_id": "2073775424665165931",
        "created_at": "2026-07-05T14:26:04.000Z",
        "edit_controls": {
          "editable_until": "2026-07-05T15:26:04.000Z",
          "edits_remaining": 5,
          "is_edit_eligible": false
        },
        "edit_history_tweet_ids": [
          "2073775424665165931"
        ],
        "entities": {
          "hashtags": [
            {
              "end": 56,
              "start": 47,
              "tag": "kigurumi"
            },
            {
              "end": 62,
              "start": 57,
              "tag": "着ぐるみ"
            },
            {
              "end": 69,
              "start": 63,
              "tag": "latex"
            }
          ],
          "mentions": [
            {
              "end": 18,
              "id": "821582303235166208",
              "start": 3,
              "username": "GoldSara_Lotus"
            },
            {
              "end": 45,
              "id": "1709241925520531456",
              "start": 35,
              "username": "Blank_qwq"
            }
          ],
          "urls": [
            {
              "display_url": "pic.x.com/e8tDq6GfrG",
              "end": 93,
              "expanded_url": "https://x.com/GoldSara_Lotus/status/2073288177650110769/photo/1",
              "media_key": "3_2073288166795288577",
              "start": 70,
              "url": "https://t.co/e8tDq6GfrG"
            }
          ]
        },
        "geo": {},
        "id": "2073775424665165931",
        "lang": "ja",
        "note_tweet": {
          "entities": {}
        },
        "possibly_sensitive": false,
        "public_metrics": {
          "bookmark_count": 0,
          "impression_count": 0,
          "like_count": 0,
          "quote_count": 0,
          "reply_count": 0,
          "retweet_count": 18
        },
        "referenced_tweets": [
          {
            "id": "2073288177650110769",
            "type": "retweeted"
          }
        ],
        "reply_settings": "everyone",
        "text": "RT @GoldSara_Lotus: 远眺雅拉和雅姆雪山🏔️\n\n📸：@Blank_qwq \n#kigurumi #着ぐるみ #latex https://t.co/e8tDq6GfrG"
      },
      {
        "article": {},
        "attachments": {
          "media_keys": [
            "3_2073288166795288577"
          ]
        },
        "author_id": "821582303235166208",
        "conversation_id": "2073288177650110769",
        "created_at": "2026-07-04T06:09:56.000Z",
        "edit_controls": {
          "editable_until": "2026-07-04T07:09:56.000Z",
          "edits_remaining": 5,
          "is_edit_eligible": true
        },
        "edit_history_tweet_ids": [
          "2073288177650110769"
        ],
        "entities": {
          "hashtags": [
            {
              "end": 36,
              "start": 27,
              "tag": "kigurumi"
            },
            {
              "end": 42,
              "start": 37,
              "tag": "着ぐるみ"
            },
            {
              "end": 49,
              "start": 43,
              "tag": "latex"
            }
          ],
          "mentions": [
            {
              "end": 25,
              "id": "1709241925520531456",
              "start": 15,
              "username": "Blank_qwq"
            }
          ],
          "urls": [
            {
              "display_url": "pic.x.com/e8tDq6GfrG",
              "end": 73,
              "expanded_url": "https://x.com/GoldSara_Lotus/status/2073288177650110769/photo/1",
              "media_key": "3_2073288166795288577",
              "start": 50,
              "url": "https://t.co/e8tDq6GfrG"
            }
          ]
        },
        "geo": {},
        "id": "2073288177650110769",
        "lang": "ja",
        "note_tweet": {
          "entities": {}
        },
        "possibly_sensitive": false,
        "public_metrics": {
          "bookmark_count": 29,
          "impression_count": 7566,
          "like_count": 250,
          "quote_count": 1,
          "reply_count": 8,
          "retweet_count": 18
        },
        "reply_settings": "everyone",
        "text": "远眺雅拉和雅姆雪山🏔️\n\n📸：@Blank_qwq \n#kigurumi #着ぐるみ #latex https://t.co/e8tDq6GfrG"
      }
    ],
    "users": [
      {
        "created_at": "2020-07-06T04:53:06.000Z",
        "derived": {
          "locations": [
            {
              "country_code": "CN",
              "full_name": "Xinpu, Jiangsu Sheng, China",
              "geo": {
                "coordinates": [
                  119.15944,
                  34.59972
                ],
                "type": "Point"
              },
              "locality": "Xinpu",
              "region": "Jiangsu Sheng"
            }
          ]
        },
        "description": "英文名叫Poca\nCN早露泡泡兔\nkiger角色：凑阿库娅，早露\n可爱对象YOYO：@vu_yoyo\n娃图专用号：@Poca5150\n欢迎大家互关贴贴",
        "entities": {
          "description": {
            "mentions": [
              {
                "end": 50,
                "start": 42,
                "username": "vu_yoyo"
              },
              {
                "end": 66,
                "start": 57,
                "username": "Poca5150"
              }
            ]
          }
        },
        "id": "1280001743162609664",
        "location": "香港",
        "name": "是早露泡泡兔呀",
        "pinned_tweet_id": "1563474617657749504",
        "profile_image_url": "https://pbs.twimg.com/profile_images/2051672456298205184/OiCCKyub_normal.jpg",
        "protected": false,
        "public_metrics": {
          "followers_count": 22512,
          "following_count": 9806,
          "like_count": 152940,
          "listed_count": 52,
          "media_count": 5235,
          "tweet_count": 53110
        },
        "url": "",
        "username": "Poca2381",
        "verified": true
      },
      {
        "created_at": "2017-01-18T04:57:40.000Z",
        "description": "可以的话，叫我小莲就好",
        "id": "821582303235166208",
        "location": "赤念堂",
        "name": "纏枝蓮",
        "pinned_tweet_id": "2022186754833617027",
        "profile_image_url": "https://pbs.twimg.com/profile_images/2022502667894095872/pPcN9kpZ_normal.jpg",
        "protected": false,
        "public_metrics": {
          "followers_count": 14340,
          "following_count": 1336,
          "like_count": 2289,
          "listed_count": 82,
          "media_count": 326,
          "tweet_count": 4875
        },
        "url": "",
        "username": "GoldSara_Lotus",
        "verified": false
      },
      {
        "created_at": "2023-10-03T16:20:26.000Z",
        "description": "💗&📷@Fishcat_0v0",
        "entities": {
          "description": {
            "mentions": [
              {
                "end": 15,
                "start": 3,
                "username": "Fishcat_0v0"
              }
            ]
          }
        },
        "id": "1709241925520531456",
        "location": "广州",
        "name": "小白",
        "pinned_tweet_id": "1993159707285246454",
        "profile_image_url": "https://pbs.twimg.com/profile_images/1968955182001328128/_Uu7Ghay_normal.jpg",
        "protected": false,
        "public_metrics": {
          "followers_count": 54501,
          "following_count": 651,
          "like_count": 5611,
          "listed_count": 210,
          "media_count": 358,
          "tweet_count": 1909
        },
        "url": "",
        "username": "Blank_qwq",
        "verified": false
      }
    ]
  }
}