{
  "data": {
    "article": {},
    "attachments": {},
    "author_id": "1280001743162609664",
    "conversation_id": "2071882539531370720",
    "created_at": "2026-06-30T10:44:24.000Z",
    "edit_controls": {
      "editable_until": "2026-06-30T11:44:24.000Z",
      "edits_remaining": 5,
      "is_edit_eligible": false
    },
    "edit_history_tweet_ids": [
      "2071907698376097907"
    ],
    "entities": {
      "mentions": [
        {
          "end": 15,
          "id": "1522542545598705664",
          "start": 0,
          "username": "Alexius_Jashin"
        }
      ]
    },
    "geo": {},
    "id": "2071907698376097907",
    "in_reply_to_user_id": "1522542545598705664",
    "lang": "zh",
    "note_tweet": {
      "entities": {}
    },
    "possibly_sensitive": false,
    "public_metrics": {
      "bookmark_count": 0,
      "impression_count": 0,
      "like_count": 0,
      "quote_count": 0,
      "reply_count": 0,
      "retweet_count": 0
    },
    "referenced_tweets": [
      {
        "id": "2071882539531370720",
        "type": "replied_to"
      }
    ],
    "reply_settings": "everyone",
    "text": "@Alexius_Jashin 啊这"
  },
  "includes": {
    "media": [
      {
        "height": 1392,
        "media_key": "3_2071882529242533888",
        "public_metrics": {},
        "type": "photo",
        "url": "https://pbs.twimg.com/media/HMDOLtvW0AAoUG-.jpg",
        "width": 1436
      }
    ],
    "tweets": [
      {
        "article": {},
        "attachments": {},
        "author_id": "1280001743162609664",
        "conversation_id": "2071882539531370720",
        "created_at": "2026-06-30T10:44:24.000Z",
        "edit_controls": {
          "editable_until": "2026-06-30T11:44:24.000Z",
          "edits_remaining": 5,
          "is_edit_eligible": false
        },
        "edit_history_tweet_ids": [
          "2071907698376097907"
        ],
        "entities": {
          "mentions": [
            {
              "end": 15,
              "id": "1522542545598705664",
              "start": 0,
              "username": "Alexius_Jashin"
            }
          ]
        },
        "geo": {},
        "id": "2071907698376097907",
        "in_reply_to_user_id": "1522542545598705664",
        "lang": "zh",
        "note_tweet": {
          "entities": {}
        },
        "possibly_sensitive": false,
        "public_metrics": {
          "bookmark_count": 0,
          "impression_count": 0,
          "like_count": 0,
          "quote_count": 0,
          "reply_count": 0,
          "retweet_count": 0
        },
        "referenced_tweets": [
          {
            "id": "2071882539531370720",
            "type": "replied_to"
          }
        ],
        "reply_settings": "everyone",
        "text": "@Alexius_Jashin 啊这"
      },
      {
        "article": {},
        "attachments": {
          "media_keys": [
            "3_2071882529242533888"
          ]
        },
        "author_id": "1522542545598705664",
        "conversation_id": "2071882539531370720",
        "created_at": "2026-06-30T09:04:25.000Z",
        "edit_controls": {
          "editable_until": "2026-06-30T10:04:25.000Z",
          "edits_remaining": 5,
          "is_edit_eligible": true
        },
        "edit_history_tweet_ids": [
          "2071882539531370720"
        ],
        "entities": {
          "urls": [
            {
              "display_url": "pic.x.com/mu1cYRqACU",
              "end": 121,
              "expanded_url": "https://x.com/Alexius_Jashin/status/2071882539531370720/photo/1",
              "media_key": "3_2071882529242533888",
              "start": 98,
              "url": "https://t.co/mu1cYRqACU"
            }
          ]
        },
        "geo": {},
        "id": "2071882539531370720",
        "lang": "zh",
        "note_tweet": {
          "entities": {}
        },
        "possibly_sensitive": false,
        "public_metrics": {
          "bookmark_count": 0,
          "impression_count": 429,
          "like_count": 10,
          "quote_count": 0,
          "reply_count": 1,
          "retweet_count": 0
        },
        "reply_settings": "everyone",
        "text": "今天最后一天ddl去吃退税，app要我注册账号注册不上要我去办税大厅注册，结果花了半个小时跑到大厅，工作人员让我多点几次多注册失败几次就能触发隐藏彩蛋用银行卡注册。。。什么鬼注册逻辑害我白跑一趟 https://t.co/mu1cYRqACU"
      }
    ],
    "users": [
      {
        "created_at": "2020-07-06T04:53:06.000Z",
        "derived": {
          "locations": [
            {
              "country_code": "CN",
              "full_name": "Xinpu, Jiangsu Sheng, China",
              "geo": {
                "coordinates": [
                  119.15944,
                  34.59972
                ],
                "type": "Point"
              },
              "locality": "Xinpu",
              "region": "Jiangsu Sheng"
            }
          ]
        },
        "description": "英文名叫Poca\nCN早露泡泡兔\nkiger角色：凑阿库娅，早露\n可爱对象YOYO：@vu_yoyo\n娃图专用号：@Poca5150\n欢迎大家互关贴贴",
        "entities": {
          "description": {
            "mentions": [
              {
                "end": 50,
                "start": 42,
                "username": "vu_yoyo"
              },
              {
                "end": 66,
                "start": 57,
                "username": "Poca5150"
              }
            ]
          }
        },
        "id": "1280001743162609664",
        "location": "香港",
        "name": "是早露泡泡兔呀",
        "pinned_tweet_id": "1563474617657749504",
        "profile_image_url": "https://pbs.twimg.com/profile_images/2051672456298205184/OiCCKyub_normal.jpg",
        "protected": false,
        "public_metrics": {
          "followers_count": 22404,
          "following_count": 9720,
          "like_count": 152807,
          "listed_count": 52,
          "media_count": 5148,
          "tweet_count": 52773
        },
        "url": "",
        "username": "Poca2381",
        "verified": true
      },
      {
        "created_at": "2022-05-06T11:43:34.000Z",
        "description": "ENBY，意面皇帝，ASD&ADHD，半吊子-(Quanter，Coder，Coser，Chef，MUGer，PoCoer，Rankeaner，Queer)，没谱-(Synthesizer，Trader，假哲批(Lacanian？))随缘发推生活吃喝玩，喜欢面面从而研究不同的人类，应该是😺，绝赞掉fo中(随缘回fo",
        "id": "1522542545598705664",
        "location": "Sasebo-shi, Nagasaki",
        "name": "松PI-ne果CO-ne💛ᩚ🤍ᩚ💜ᩚ🖤ᩚAlexius",
        "profile_image_url": "https://pbs.twimg.com/profile_images/2010733193021009920/R8lNwN8i_normal.jpg",
        "protected": false,
        "public_metrics": {
          "followers_count": 3936,
          "following_count": 1862,
          "like_count": 9298,
          "listed_count": 6,
          "media_count": 815,
          "tweet_count": 5408
        },
        "url": "",
        "username": "Alexius_Jashin",
        "verified": false
      }
    ]
  }
}