{
  "data": {
    "article": {},
    "attachments": {},
    "author_id": "1280001743162609664",
    "conversation_id": "2058569431736070405",
    "created_at": "2026-05-25T05:41:55.000Z",
    "edit_controls": {
      "editable_until": "2026-05-25T06:41:55.000Z",
      "edits_remaining": 5,
      "is_edit_eligible": false
    },
    "edit_history_tweet_ids": [
      "2058785615404265888"
    ],
    "entities": {
      "mentions": [
        {
          "end": 12,
          "id": "2497764032",
          "start": 0,
          "username": "TainiiMikan"
        }
      ]
    },
    "geo": {},
    "id": "2058785615404265888",
    "in_reply_to_user_id": "2497764032",
    "lang": "zh",
    "note_tweet": {
      "entities": {}
    },
    "possibly_sensitive": false,
    "public_metrics": {
      "bookmark_count": 0,
      "impression_count": 0,
      "like_count": 0,
      "quote_count": 0,
      "reply_count": 0,
      "retweet_count": 0
    },
    "referenced_tweets": [
      {
        "id": "2058569431736070405",
        "type": "replied_to"
      }
    ],
    "reply_settings": "everyone",
    "text": "@TainiiMikan 乐"
  },
  "includes": {
    "media": [
      {
        "height": 360,
        "media_key": "3_2058569378569056256",
        "public_metrics": {},
        "type": "photo",
        "url": "https://pbs.twimg.com/media/HJGB8Wsa8AAwV0Q.jpg",
        "width": 564
      }
    ],
    "tweets": [
      {
        "article": {},
        "attachments": {},
        "author_id": "1280001743162609664",
        "conversation_id": "2058569431736070405",
        "created_at": "2026-05-25T05:41:55.000Z",
        "edit_controls": {
          "editable_until": "2026-05-25T06:41:55.000Z",
          "edits_remaining": 5,
          "is_edit_eligible": false
        },
        "edit_history_tweet_ids": [
          "2058785615404265888"
        ],
        "entities": {
          "mentions": [
            {
              "end": 12,
              "id": "2497764032",
              "start": 0,
              "username": "TainiiMikan"
            }
          ]
        },
        "geo": {},
        "id": "2058785615404265888",
        "in_reply_to_user_id": "2497764032",
        "lang": "zh",
        "note_tweet": {
          "entities": {}
        },
        "possibly_sensitive": false,
        "public_metrics": {
          "bookmark_count": 0,
          "impression_count": 0,
          "like_count": 0,
          "quote_count": 0,
          "reply_count": 0,
          "retweet_count": 0
        },
        "referenced_tweets": [
          {
            "id": "2058569431736070405",
            "type": "replied_to"
          }
        ],
        "reply_settings": "everyone",
        "text": "@TainiiMikan 乐"
      },
      {
        "article": {},
        "attachments": {
          "media_keys": [
            "3_2058569378569056256"
          ]
        },
        "author_id": "2497764032",
        "conversation_id": "2058569431736070405",
        "created_at": "2026-05-24T15:22:53.000Z",
        "edit_controls": {
          "editable_until": "2026-05-24T16:22:53.000Z",
          "edits_remaining": 5,
          "is_edit_eligible": true
        },
        "edit_history_tweet_ids": [
          "2058569431736070405"
        ],
        "entities": {
          "urls": [
            {
              "display_url": "pic.x.com/GTBQXYXB3W",
              "end": 30,
              "expanded_url": "https://x.com/TainiiMikan/status/2058569431736070405/photo/1",
              "media_key": "3_2058569378569056256",
              "start": 7,
              "url": "https://t.co/GTBQXYXB3W"
            }
          ]
        },
        "geo": {},
        "id": "2058569431736070405",
        "lang": "ja",
        "note_tweet": {
          "entities": {}
        },
        "possibly_sensitive": false,
        "public_metrics": {
          "bookmark_count": 6,
          "impression_count": 10414,
          "like_count": 145,
          "quote_count": 0,
          "reply_count": 18,
          "retweet_count": 0
        },
        "reply_settings": "everyone",
        "text": "我也有今天🥺 https://t.co/GTBQXYXB3W"
      }
    ],
    "users": [
      {
        "created_at": "2020-07-06T04:53:06.000Z",
        "derived": {
          "locations": [
            {
              "country_code": "CN",
              "full_name": "Xinpu, Jiangsu Sheng, China",
              "geo": {
                "coordinates": [
                  119.15944,
                  34.59972
                ],
                "type": "Point"
              },
              "locality": "Xinpu",
              "region": "Jiangsu Sheng"
            }
          ]
        },
        "description": "英文名叫Poca\nCN早露泡泡兔\nkiger角色：凑阿库娅，早露（制作中）\n可爱对象YOYO：@vu_yoyo\n娃图专用号：@Poca5150\n欢迎大家互关贴贴",
        "entities": {
          "description": {
            "mentions": [
              {
                "end": 55,
                "start": 47,
                "username": "vu_yoyo"
              },
              {
                "end": 71,
                "start": 62,
                "username": "Poca5150"
              }
            ]
          }
        },
        "id": "1280001743162609664",
        "location": "香港",
        "name": "是早露泡泡兔呀",
        "pinned_tweet_id": "1563474617657749504",
        "profile_image_url": "https://pbs.twimg.com/profile_images/2051672456298205184/OiCCKyub_normal.jpg",
        "protected": false,
        "public_metrics": {
          "followers_count": 20917,
          "following_count": 8428,
          "like_count": 151114,
          "listed_count": 51,
          "media_count": 4333,
          "tweet_count": 49286
        },
        "username": "Poca2381",
        "verified": true
      },
      {
        "created_at": "2014-05-16T05:06:00.000Z",
        "description": "是一只，后面忘了，总之是杂鱼酱 || 女装号: @JanboMikan",
        "entities": {
          "description": {
            "mentions": [
              {
                "end": 35,
                "start": 24,
                "username": "JanboMikan"
              }
            ]
          }
        },
        "id": "2497764032",
        "location": "鱼缸",
        "name": "タイニー蜜柑",
        "profile_image_url": "https://pbs.twimg.com/profile_images/1996230563334934528/UuZF-Uhr_normal.jpg",
        "protected": false,
        "public_metrics": {
          "followers_count": 771,
          "following_count": 122,
          "like_count": 1061,
          "listed_count": 1,
          "media_count": 97,
          "tweet_count": 906
        },
        "username": "TainiiMikan",
        "verified": false
      }
    ]
  }
}