{
  "data": {
    "article": {},
    "attachments": {},
    "author_id": "1280001743162609664",
    "conversation_id": "2065897359574462876",
    "created_at": "2026-06-14T10:11:19.000Z",
    "edit_controls": {
      "editable_until": "2026-06-14T11:11:19.000Z",
      "edits_remaining": 5,
      "is_edit_eligible": false
    },
    "edit_history_tweet_ids": [
      "2066101166581457109"
    ],
    "entities": {
      "mentions": [
        {
          "end": 10,
          "id": "1982449259774656512",
          "start": 0,
          "username": "smiroyama"
        }
      ]
    },
    "geo": {},
    "id": "2066101166581457109",
    "in_reply_to_user_id": "1982449259774656512",
    "lang": "zh",
    "note_tweet": {
      "entities": {}
    },
    "possibly_sensitive": false,
    "public_metrics": {
      "bookmark_count": 0,
      "impression_count": 0,
      "like_count": 0,
      "quote_count": 0,
      "reply_count": 0,
      "retweet_count": 0
    },
    "referenced_tweets": [
      {
        "id": "2065897359574462876",
        "type": "replied_to"
      }
    ],
    "reply_settings": "everyone",
    "text": "@smiroyama 太强了"
  },
  "includes": {
    "media": [
      {
        "height": 2048,
        "media_key": "3_2065897347973103616",
        "public_metrics": {},
        "type": "photo",
        "url": "https://pbs.twimg.com/media/HKuKsUBbwAAw5Zh.jpg",
        "width": 946
      }
    ],
    "tweets": [
      {
        "article": {},
        "attachments": {},
        "author_id": "1280001743162609664",
        "conversation_id": "2065897359574462876",
        "created_at": "2026-06-14T10:11:19.000Z",
        "edit_controls": {
          "editable_until": "2026-06-14T11:11:19.000Z",
          "edits_remaining": 5,
          "is_edit_eligible": false
        },
        "edit_history_tweet_ids": [
          "2066101166581457109"
        ],
        "entities": {
          "mentions": [
            {
              "end": 10,
              "id": "1982449259774656512",
              "start": 0,
              "username": "smiroyama"
            }
          ]
        },
        "geo": {},
        "id": "2066101166581457109",
        "in_reply_to_user_id": "1982449259774656512",
        "lang": "zh",
        "note_tweet": {
          "entities": {}
        },
        "possibly_sensitive": false,
        "public_metrics": {
          "bookmark_count": 0,
          "impression_count": 0,
          "like_count": 0,
          "quote_count": 0,
          "reply_count": 0,
          "retweet_count": 0
        },
        "referenced_tweets": [
          {
            "id": "2065897359574462876",
            "type": "replied_to"
          }
        ],
        "reply_settings": "everyone",
        "text": "@smiroyama 太强了"
      },
      {
        "article": {},
        "attachments": {
          "media_keys": [
            "3_2065897347973103616"
          ]
        },
        "author_id": "1982449259774656512",
        "conversation_id": "2065897359574462876",
        "created_at": "2026-06-13T20:41:27.000Z",
        "edit_controls": {
          "editable_until": "2026-06-13T21:41:27.000Z",
          "edits_remaining": 5,
          "is_edit_eligible": true
        },
        "edit_history_tweet_ids": [
          "2065897359574462876"
        ],
        "entities": {
          "urls": [
            {
              "display_url": "pic.x.com/3at4oT1rb5",
              "end": 49,
              "expanded_url": "https://x.com/smiroyama/status/2065897359574462876/photo/1",
              "media_key": "3_2065897347973103616",
              "start": 26,
              "url": "https://t.co/3at4oT1rb5"
            }
          ]
        },
        "geo": {},
        "id": "2065897359574462876",
        "lang": "zh",
        "note_tweet": {
          "entities": {}
        },
        "possibly_sensitive": false,
        "public_metrics": {
          "bookmark_count": 0,
          "impression_count": 3893,
          "like_count": 66,
          "quote_count": 0,
          "reply_count": 23,
          "retweet_count": 0
        },
        "reply_settings": "everyone",
        "text": "祝愿大家六级都通过喵🐱\n（本人去年 12 月考的） https://t.co/3at4oT1rb5"
      }
    ],
    "users": [
      {
        "created_at": "2020-07-06T04:53:06.000Z",
        "derived": {
          "locations": [
            {
              "country_code": "CN",
              "full_name": "Xinpu, Jiangsu Sheng, China",
              "geo": {
                "coordinates": [
                  119.15944,
                  34.59972
                ],
                "type": "Point"
              },
              "locality": "Xinpu",
              "region": "Jiangsu Sheng"
            }
          ]
        },
        "description": "英文名叫Poca\nCN早露泡泡兔\nkiger角色：凑阿库娅，早露（制作中）\n可爱对象YOYO：@vu_yoyo\n娃图专用号：@Poca5150\n欢迎大家互关贴贴",
        "entities": {
          "description": {
            "mentions": [
              {
                "end": 55,
                "start": 47,
                "username": "vu_yoyo"
              },
              {
                "end": 71,
                "start": 62,
                "username": "Poca5150"
              }
            ]
          }
        },
        "id": "1280001743162609664",
        "location": "香港",
        "name": "是早露泡泡兔呀",
        "pinned_tweet_id": "1563474617657749504",
        "profile_image_url": "https://pbs.twimg.com/profile_images/2051672456298205184/OiCCKyub_normal.jpg",
        "protected": false,
        "public_metrics": {
          "followers_count": 21855,
          "following_count": 9319,
          "like_count": 152189,
          "listed_count": 52,
          "media_count": 4802,
          "tweet_count": 51439
        },
        "username": "Poca2381",
        "verified": true
      },
      {
        "created_at": "2025-10-26T14:08:58.000Z",
        "description": "Developing https://t.co/pJ9VtduSxe | friends: @Huang_Yut1ng @fukui_p26 好伙伴: @qianxunchan",
        "entities": {
          "description": {
            "mentions": [
              {
                "end": 59,
                "start": 46,
                "username": "Huang_Yut1ng"
              },
              {
                "end": 70,
                "start": 60,
                "username": "fukui_p26"
              },
              {
                "end": 88,
                "start": 76,
                "username": "qianxunchan"
              }
            ],
            "urls": [
              {
                "display_url": "hrt.mahiro.uk",
                "end": 34,
                "expanded_url": "http://hrt.mahiro.uk",
                "start": 11,
                "url": "https://t.co/pJ9VtduSxe"
              }
            ]
          },
          "url": {
            "urls": [
              {
                "display_url": "mizukiakiyama.com",
                "end": 23,
                "expanded_url": "http://mizukiakiyama.com",
                "start": 0,
                "url": "https://t.co/YPl1rDopW0"
              }
            ]
          }
        },
        "id": "1982449259774656512",
        "location": "绪山寺",
        "name": "Smirnova 🏳️‍⚧️🍡",
        "pinned_tweet_id": "2065373003169570821",
        "profile_image_url": "https://pbs.twimg.com/profile_images/2064928216654217216/gHEvZe0i_normal.jpg",
        "protected": false,
        "public_metrics": {
          "followers_count": 6673,
          "following_count": 2404,
          "like_count": 13032,
          "listed_count": 21,
          "media_count": 2121,
          "tweet_count": 7786
        },
        "url": "https://t.co/YPl1rDopW0",
        "username": "smiroyama",
        "verified": true
      }
    ]
  }
}